Metadata-Version: 2.1
Name: pctl-scale
Version: 0.1.1
Summary: Scale a variable into an open interval (0,1) whereas values within a given lower and upper percentile maintain a linear relation, and outlier saturate towards the interval limits.
Home-page: http://github.com/kmedian/pctl_scale
Author: Ulf Hamster
Author-email: 554c46@gmail.com
License: MIT
Platform: UNKNOWN
Requires-Python: >=3.6
